ss_dos/__init__.py
ss_dos/ss_dos.py
ss_dos-3.0.0.dist-info/METADATA
ss_dos-3.0.0.dist-info/WHEEL
ss_dos-3.0.0.dist-info/top_level.txt
ss_dos-3.0.0.dist-info/RECORD
