Metadata-Version: 2.1
Name: ss-dos
Version: 3.0.0
Summary: fix some problems
Home-page: UNKNOWN
Author: enygames
License: UNKNOWN
Platform: UNKNOWN
Classifier: Programming Language :: Python :: 3
Classifier: License :: OSI Approved :: MIT License
Classifier: Operating System :: OS Independent
Requires-Python: >=3.6
